openai_chat_parser/__init__.py
openai_chat_parser/__main__.py
openai_chat_parser-0.1.0.dist-info/LICENSE
openai_chat_parser-0.1.0.dist-info/METADATA
openai_chat_parser-0.1.0.dist-info/WHEEL
openai_chat_parser-0.1.0.dist-info/entry_points.txt
openai_chat_parser-0.1.0.dist-info/top_level.txt
openai_chat_parser-0.1.0.dist-info/RECORD
